mkdocs_diagrams/__init__.py
mkdocs_diagrams/plugin.py
mkdocs_diagrams_plugin-2.0.1.dist-info/LICENSE
mkdocs_diagrams_plugin-2.0.1.dist-info/METADATA
mkdocs_diagrams_plugin-2.0.1.dist-info/WHEEL
mkdocs_diagrams_plugin-2.0.1.dist-info/entry_points.txt
mkdocs_diagrams_plugin-2.0.1.dist-info/RECORD
