Metadata-Version: 2.1
Name: mkdocs-diagrams-plugin
Version: 2.0.1
Summary: MkDocs plugin to render Diagrams files
License: MIT
Author: Marco Ceppi
Author-email: marco@ceppi.net
Requires-Python: >=3.8,<4.0
Classifier: License :: OSI Approved :: MIT License
Classifier: Programming Language :: Python :: 3
Classifier: Programming Language :: Python :: 3.8
Classifier: Programming Language :: Python :: 3.9
Classifier: Programming Language :: Python :: 3.10
Classifier: Programming Language :: Python :: 3.11
Classifier: Programming Language :: Python :: 3.12
Requires-Dist: diagrams (>=0.23.4,<0.24.0)
Requires-Dist: mkdocs (>=1.5.3,<2.0.0)
